data_python_davitgog/__init__.py
data_python_davitgog/base.py
data_python_davitgog-0.0.4.dist-info/LICENSE
data_python_davitgog-0.0.4.dist-info/METADATA
data_python_davitgog-0.0.4.dist-info/WHEEL
data_python_davitgog-0.0.4.dist-info/top_level.txt
data_python_davitgog-0.0.4.dist-info/RECORD
